analysis/__init__.py
analysis/dbutils.py
analysis/handle.py
analysis/service.py
config/__init__.py
crawler/__init__.py
crawler/items.py
crawler/main.py
crawler/middlewares.py
crawler/pipelines.py
crawler/settings.py
crawler/db/__init__.py
crawler/db/db.py
crawler/db/db_config.py
crawler/keywords/__init__.py
crawler/keywords/keywords.py
crawler/model/__init__.py
crawler/model/dao.py
crawler/model/tables.py
crawler/nlpapi/__init__.py
crawler/nlpapi/baidu_aip.py
crawler/nlpapi/config.py
crawler/nlpapi/core.py
crawler/spiders/BaiduNewsSpider.py
crawler/spiders/BaiduSpider.py
crawler/spiders/PeopleDailySpider.py
crawler/spiders/QQNewsSpider.py
crawler/spiders/TestRedisSpider.py
crawler/spiders/__init__.py
crawler/spiders/config.py
crawler/utility/__init__.py
crawler/utility/chrome_driver.py
crawler/utility/constants.py
crawler/utility/preprocesss.py
crawler/utility/request2response.py
news_analysis/__init__.py
news_analysis/dbutils.py
news_analysis/handle.py
news_analysis/service.py
nlp/__init__.py
nlp/baidu.py
nlp/preprocess.py
nlp/test1.py
nlp/test2.py
nlp/test3.py
nlp/test4.py
nlp/test5.py
nlp/custome/__init__.py
nlp/custome/test.py
nlp/custome/test2.py
pubopinion-0.1.0a3.dist-info/METADATA
pubopinion-0.1.0a3.dist-info/WHEEL
pubopinion-0.1.0a3.dist-info/top_level.txt
pubopinion-0.1.0a3.dist-info/RECORD
