Metadata-Version: 2.1
Name: pubopinion
Version: 0.1.0a3
Summary: public opinion module
Home-page: https://gitlab.com/dzywork/cadrem-pubopinion-crawler.git
Author: 戴志勇
Author-email: dzywork@Outlook.com
License: MIT
Keywords: crawler scrapy python
Platform: UNKNOWN
Classifier: Programming Language :: Python :: 3
Classifier: License :: OSI Approved :: MIT License
Classifier: Operating System :: OS Independent
Requires-Python: >=3.6
